{"items":[],"diceLists":{"d4":["Light Rain","Pouring Rain","Overcast","Dense Fog"],"d6":["Old Growth","Flooded","Islands","New Growth","Walking Path","Washed Out Roads"],"d8":["Faery Tree","Bone Piles","Magical Tear","Campsite","Talking Lamp Post","Blood Tree's","Hangmans Tree","Ancient Tree"],"d10":["Pumpkin Patch","Witches Hut","Vultures","Boat","Totem","Skeleton Creeps","Heavvy Foliage","Haunted Cemetary","Grove","Briar Patch"],"d12":["Shrine","Skorme Temple","Necropolis","Fortune Teller","Hunters Cabin","Ruins","Farm","Smugglers Cache","Burial Mound","Watermill","Ruined Fort","Village (Protected)"],"d20":["Wraith","Gruesome George","Mistmourn Shaman","Zombies","Plants","Mushrooms","Ghosts","Spiders Den","Skullbats","Scarecrow Construct","Dead Adventurers","Witches Coven","Abandoned Mine","Markerstone","Sunken Tower","Mine Entrance","Underwater Cave","Stone Henge","Peasant Militia","Faery Dragon"]}}